aiida_phonopy/__init__.py
aiida_phonopy/calculations/__init__.py
aiida_phonopy/calculations/phonopy.py
aiida_phonopy/calculations/functions/__init__.py
aiida_phonopy/calculations/functions/data_utils.py
aiida_phonopy/calculations/functions/link_structures.py
aiida_phonopy/data/__init__.py
aiida_phonopy/data/force_constants.py
aiida_phonopy/data/phonopy.py
aiida_phonopy/data/preprocess.py
aiida_phonopy/data/raw.py
aiida_phonopy/parsers/__init__.py
aiida_phonopy/parsers/base.py
aiida_phonopy/parsers/phonopy.py
aiida_phonopy/parsers/raw_parsers/__init__.py
aiida_phonopy/parsers/raw_parsers/phonopy.py
aiida_phonopy/utils/__init__.py
aiida_phonopy/utils/mapping.py
aiida_phonopy/utils/resources.py
aiida_phonopy/utils/validators.py
aiida_phonopy/workflows/__init__.py
aiida_phonopy/workflows/ase.py
aiida_phonopy/workflows/phonopy.py
aiida_phonopy-1.3.0.dist-info/entry_points.txt
aiida_phonopy-1.3.0.dist-info/licenses/LICENSE.txt
aiida_phonopy-1.3.0.dist-info/WHEEL
aiida_phonopy-1.3.0.dist-info/METADATA
aiida_phonopy-1.3.0.dist-info/RECORD
